README.md
setup.py
djtezos/__init__.py
djtezos/admin.py
djtezos/crudlfap.py
djtezos/demo.py
djtezos/exceptions.py
djtezos/fake.py
djtezos/models.py
djtezos/provider.py
djtezos/serializers.py
djtezos/test_models.py
djtezos/test_settings.py
djtezos/test_spooler.py
djtezos/tezos.py
djtezos/views.py
djtezos.egg-info/PKG-INFO
djtezos.egg-info/SOURCES.txt
djtezos.egg-info/dependency_links.txt
djtezos.egg-info/requires.txt
djtezos.egg-info/top_level.txt
djtezos/management/__init__.py
djtezos/management/commands/__init__.py
djtezos/management/commands/djtezos_balance.py
djtezos/management/commands/djtezos_sync.py
djtezos/management/commands/djtezos_write.py
djtezos/migrations/0001_initial.py
djtezos/migrations/0002_contract_source.py
djtezos/migrations/0003_account_created_updated_at.py
djtezos/migrations/0004_alter_transaction_amount.py
djtezos/migrations/0005_alter_transaction_function.py
djtezos/migrations/0006_transaction_args_mich.py
djtezos/migrations/0007_account_balance.py
djtezos/migrations/0008_account_name.py
djtezos/migrations/0009_transaction_level.py
djtezos/migrations/0010_levels.py
djtezos/migrations/0011_last_fail.py
djtezos/migrations/0012_transaction_users.py
djtezos/migrations/__init__.py