Metadata-Version: 2.1
Name: djtezos
Version: 0.5.1
Summary: Django-Tezos
Home-page: https://yourlabs.io/oss/cli2
Author: James Pic
Author-email: jamespic@gmail.com
License: MIT
Keywords: cli
Platform: UNKNOWN
Requires-Python: >=3.8
Provides-Extra: test
